gaeb_parser/__init__.py
gaeb_parser/example_usage.py
gaeb_parser/xml_gaeb_parser.py
gaeb_parser-0.1.2.dist-info/licenses/LICENSE
tests/test_xml_gaeb_parser.py
gaeb_parser-0.1.2.dist-info/METADATA
gaeb_parser-0.1.2.dist-info/WHEEL
gaeb_parser-0.1.2.dist-info/top_level.txt
gaeb_parser-0.1.2.dist-info/RECORD
