Metadata-Version: 2.4
Name: gaeb-parser
Version: 0.1.2
Summary: parses xml gaeb files and converts them to a pandas dataframe
Author-email: Lucas Carlier <mail@carlier.info>
License: MIT
Project-URL: Homepage, https://github.com/meindonut/gaeb-parser
Project-URL: Issues, https://github.com/meindonut/gaeb-parser/issues
Requires-Python: >=3.9
License-File: LICENSE
Requires-Dist: pandas>=1.3.0
Requires-Dist: beautifulsoup4>=4.10.0
Requires-Dist: lxml>=5.4.0
Dynamic: license-file
